{
	"name": "DelimitedText1",
	"properties": {
		"linkedServiceName": {
			"referenceName": "LS_BlobStorage_DEV",
			"type": "LinkedServiceReference"
		},
		"parameters": {
			"container": {
				"type": "string"
			},
			"folder": {
				"type": "string"
			}
		},
		"annotations": [],
		"type": "DelimitedText",
		"typeProperties": {
			"location": {
				"type": "AzureBlobStorageLocation",
				"folderPath": {
					"value": "@dataset().folder",
					"type": "Expression"
				},
				"container": {
					"value": "@dataset().container",
					"type": "Expression"
				}
			},
			"columnDelimiter": ",",
			"escapeChar": "\\",
			"quoteChar": "\""
		},
		"schema": []
	}
}